mbtiles_util/__init__.py
mbtiles_util/folder2s3.py
mbtiles_util/mbtiles2folder.py
mbtiles_util/mbtiles2s3.py
mbtiles_util/mbtilesinfo.py
mbtiles_util/osm2geojson.py
mbtiles_util/osm2mbtiles.py
mbtiles_util/osm2streets.py
mbtiles_util/tileserve.py
mbtiles_util/tms2xyz.py
mbtiles_util/tms2xyz_raster.py
mbtiles_util/util.py
mbtiles_util-1.0.4.dist-info/LICENSE
mbtiles_util-1.0.4.dist-info/METADATA
mbtiles_util-1.0.4.dist-info/WHEEL
mbtiles_util-1.0.4.dist-info/entry_points.txt
mbtiles_util-1.0.4.dist-info/top_level.txt
mbtiles_util-1.0.4.dist-info/RECORD
