Metadata-Version: 2.1
Name: mbtiles-util
Version: 1.0.4
Summary: MBTiles Utilities
Home-page: https://github.com/thangqd/mbtiles_util
Author: Thang Quach
Author-email: quachdongthang@gmail.com
Classifier: Programming Language :: Python :: 3
Classifier: Environment :: Console
Classifier: Topic :: Scientific/Engineering :: GIS
Classifier: License :: OSI Approved :: MIT License
Classifier: Operating System :: OS Independent
License-File: LICENSE
Requires-Dist: boto3 ~=1.34.72
